dictation/__init__.py
dictation/version.txt
dictation-1.0.0.dist-info/LICENSE.md
dictation-1.0.0.dist-info/METADATA
dictation-1.0.0.dist-info/WHEEL
dictation-1.0.0.dist-info/top_level.txt
dictation-1.0.0.dist-info/zip-safe
dictation-1.0.0.dist-info/RECORD
