Metadata-Version: 2.2
Name: dictation
Version: 1.0.0
Summary: Annotated dictionaries for Python
Author: Daniel Sissman
License: MIT License
Project-URL: Documentation, https://github.com/bluebinary/dictation/blob/main/README.md
Project-URL: Changelog, https://github.com/bluebinary/dictation/blob/main/CHANGELOG.md
Project-URL: Repository, https://github.com/bluebinary/dictation
Project-URL: Issues, https://github.com/bluebinary/dictation/issues
Keywords: dictionary,dict,annotated dictionary
Classifier: License :: OSI Approved :: MIT License
Classifier: Programming Language :: Python :: 3
Classifier: Programming Language :: Python :: 3.9
Classifier: Programming Language :: Python :: 3.10
Classifier: Programming Language :: Python :: 3.11
Classifier: Programming Language :: Python :: 3.12
Classifier: Programming Language :: Python :: 3.13
Requires-Python: >=3.9
License-File: LICENSE.md
